sbc_model/__init__.py
sbc_model/model.py
sbc_model-0.2.1.dist-info/licenses/LICENSE
sbc_model-0.2.1.dist-info/METADATA
sbc_model-0.2.1.dist-info/WHEEL
sbc_model-0.2.1.dist-info/top_level.txt
sbc_model-0.2.1.dist-info/RECORD
