Metadata-Version: 2.4
Name: sbc-model
Version: 0.2.1
Summary: Un clasificador de Machine Learning que implementa un ensamblaje de Stacking con modelos de Boosting.
Author-email: Pablo Eduardo Chavez Mercado <pablo.chavez1992@gmail.com>
License: MIT License
Keywords: stacking,boosting,classifier,ensemble,xgboost,machine-learning
Classifier: Development Status :: 3 - Alpha
Classifier: Intended Audience :: Developers
Classifier: Intended Audience :: Science/Research
Classifier: License :: OSI Approved :: MIT License
Classifier: Programming Language :: Python :: 3
Classifier: Programming Language :: Python :: 3.8
Classifier: Programming Language :: Python :: 3.9
Classifier: Programming Language :: Python :: 3.10
Classifier: Programming Language :: Python :: 3.11
Classifier: Programming Language :: Python :: 3.12
Classifier: Topic :: Scientific/Engineering :: Artificial Intelligence
Classifier: Topic :: Software Development :: Libraries :: Python Modules
Requires-Python: >=3.8
License-File: LICENSE
Requires-Dist: numpy
Requires-Dist: scikit-learn
Requires-Dist: xgboost
Requires-Dist: lightgbm
Requires-Dist: catboost
Requires-Dist: pandas
Dynamic: license-file
